CHANGELOG.md
LICENSE
MANIFEST.in
README.md
setup.py
jsonrpcclient/__init__.py
jsonrpcclient/__main__.py
jsonrpcclient/async_client.py
jsonrpcclient/client.py
jsonrpcclient/config.py
jsonrpcclient/exceptions.py
jsonrpcclient/id_generators.py
jsonrpcclient/log.py
jsonrpcclient/parse.py
jsonrpcclient/requests.py
jsonrpcclient/response-schema.json
jsonrpcclient/response.py
jsonrpcclient.egg-info/PKG-INFO
jsonrpcclient.egg-info/SOURCES.txt
jsonrpcclient.egg-info/dependency_links.txt
jsonrpcclient.egg-info/entry_points.txt
jsonrpcclient.egg-info/not-zip-safe
jsonrpcclient.egg-info/requires.txt
jsonrpcclient.egg-info/top_level.txt
jsonrpcclient/clients/__init__.py
jsonrpcclient/clients/aiohttp_client.py
jsonrpcclient/clients/http_client.py
jsonrpcclient/clients/socket_client.py
jsonrpcclient/clients/tornado_client.py
jsonrpcclient/clients/websockets_client.py
jsonrpcclient/clients/zeromq_client.py