Metadata-Version: 2.1
Name: jsonrpcclient
Version: 3.3.5
Summary: Send JSON-RPC requests
Home-page: https://github.com/bcb/jsonrpcclient
Author: Beau Barker
Author-email: beauinmelbourne@gmail.com
License: MIT
Platform: UNKNOWN
Classifier: Programming Language :: Python :: 3.5
Classifier: Programming Language :: Python :: 3.6
Classifier: Programming Language :: Python :: 3.7
Classifier: Programming Language :: Python :: 3.8
Provides-Extra: tornado
Provides-Extra: aiohttp
Provides-Extra: requests
Provides-Extra: requests_security
Provides-Extra: zmq
Provides-Extra: websockets
Provides-Extra: unittest
